iic4sem/__init__.py
iic4sem/broadcast_server.py
iic4sem/echo_server.py
iic4sem/http_server.py
iic4sem/iic4sem.cfg
iic4sem/libevent_server.py
iic4sem/serial_server.py
iic4sem-0.1.1.post4.data/scripts/iic4sem
iic4sem-0.1.1.post4.dist-info/DESCRIPTION.rst
iic4sem-0.1.1.post4.dist-info/METADATA
iic4sem-0.1.1.post4.dist-info/RECORD
iic4sem-0.1.1.post4.dist-info/WHEEL
iic4sem-0.1.1.post4.dist-info/metadata.json
iic4sem-0.1.1.post4.dist-info/top_level.txt
