Metadata-Version: 2.0
Name: iic4sem
Version: 0.1.1.post4
Summary: Basic Network Programming Assignments For IIC, UDSC 4 Sem Final
Home-page: https://github.com/xandfury/iic4sem
Author: Abhinav Saxena
Author-email: abhinav.saxena@iic.ac.in
License: GPL 3
Keywords: IIC UDSC
Platform: UNKNOWN
Classifier: Development Status :: 3 - Alpha
Classifier: Environment :: Console
Classifier: Intended Audience :: Developers
Classifier: License :: OSI Approved :: GNU General Public License v3 (GPLv3)
Classifier: Operating System :: POSIX :: Linux
Classifier: Programming Language :: Python :: 3
Classifier: Programming Language :: Python :: 3.5
Classifier: Programming Language :: Python :: 3.6
Requires-Dist: pyserial
Requires-Dist: gevent
Requires-Dist: requests
